beautools/__init__.py
beautools/cycler.py
beautools/decor.py
beautools/defaultrepo.py
beautools/files.py
beautools/funcs.py
beautools/hot_cycler.py
beautools/repobase.py
beautools/repomixins.py
beautools/testools.py
beautools/utils.py
beautools/yamlfile.py
beautools-1.2.2.dist-info/METADATA
beautools-1.2.2.dist-info/WHEEL
beautools-1.2.2.dist-info/licenses/LICENSE
beautools-1.2.2.dist-info/RECORD
