Metadata-Version: 2.4
Name: beautools
Version: 1.2.2
Summary: Cool beautiful tools for python.
Author-email: Dmitor cel Mare <dmeety@yandex.ru>
License-File: LICENSE
Requires-Dist: pyyaml
Requires-Dist: sqlalchemy
Requires-Dist: yamlordereddictloader
Provides-Extra: dev
Requires-Dist: pytest; extra == 'dev'
